scanspec/__init__.py
scanspec/__main__.py
scanspec/_version.py
scanspec/cli.py
scanspec/core.py
scanspec/plot.py
scanspec/service.py
scanspec/specs.py
scanspec/sphinxext.py
scanspec-0.9.1.dist-info/licenses/LICENSE
scanspec-0.9.1.dist-info/METADATA
scanspec-0.9.1.dist-info/WHEEL
scanspec-0.9.1.dist-info/entry_points.txt
scanspec-0.9.1.dist-info/top_level.txt
scanspec-0.9.1.dist-info/RECORD
