Metadata-Version: 2.4
Name: scanspec
Version: 0.9.1
Summary: Specify step and flyscan paths in a serializable, efficient and Pythonic way
Author-email: Tom Cobb <tom.cobb@diamond.ac.uk>
License:                                  Apache License
Project-URL: GitHub, https://github.com/bluesky/scanspec
Classifier: Development Status :: 3 - Alpha
Classifier: License :: OSI Approved :: Apache Software License
Classifier: Programming Language :: Python :: 3.11
Classifier: Programming Language :: Python :: 3.12
Classifier: Programming Language :: Python :: 3.13
Requires-Python: >=3.11
License-File: LICENSE
Requires-Dist: numpy
Requires-Dist: click>=8.1
Requires-Dist: pydantic>=2.0
Provides-Extra: plotting
Requires-Dist: scipy; extra == "plotting"
Requires-Dist: matplotlib; extra == "plotting"
Provides-Extra: service
Requires-Dist: fastapi>=0.100.0; extra == "service"
Requires-Dist: uvicorn; extra == "service"
Dynamic: license-file
